uc_manager-0.1.0rc2.dist-info/licenses/LICENSE
ucm/__init__.py
ucm/logger.py
ucm/integration/__init__.py
ucm/integration/vllm/__init__.py
ucm/integration/vllm/monkeypatch.py
ucm/integration/vllm/uc_connector.py
ucm/integration/vllm/patch/__init__.py
ucm/integration/vllm/patch/apply_patch.py
ucm/integration/vllm/patch/monkey_patch.py
ucm/integration/vllm/patch/monkeypatch.py
ucm/integration/vllm/patch/vllm_adapt_aggre_monkey_patch.py
ucm/integration/vllm/patch/vllm_adapt_pc_monkey_patch.py
ucm/integration/vllm/patch/vllm_adapt_sparse_monkey_patch.py
ucm/integration/vllm/patch/vllm_ascend_adapt_monkey_patch.py
ucm/integration/vllm/patch/monkeypatch/__init__.py
ucm/integration/vllm/patch/monkeypatch/v091/__init__.py
ucm/integration/vllm/patch/monkeypatch/v091/vllm_adapt.py
ucm/integration/vllm/patch/monkeypatch/v091/vllm_ascend_adapt.py
ucm/integration/vllm/patch/monkeypatch/v092/__init__.py
ucm/integration/vllm/patch/monkeypatch/v092/vllm_adapt_aggre.py
ucm/integration/vllm/patch/monkeypatch/v092/vllm_adapt_pc.py
ucm/integration/vllm/patch/monkeypatch/v092/vllm_adapt_sparse.py
ucm/integration/vllm/patch/monkeypatch/v092/vllm_ascend_adapt.py
ucm/integration/vllm/patch/patch_funcs/__init__.py
ucm/integration/vllm/patch/patch_funcs/v091/__init__.py
ucm/integration/vllm/patch/patch_funcs/v091/vllm_adapt.py
ucm/integration/vllm/patch/patch_funcs/v091/vllm_ascend_adapt.py
ucm/integration/vllm/patch/patch_funcs/v092/__init__.py
ucm/integration/vllm/patch/patch_funcs/v092/vllm_adapt.py
ucm/integration/vllm/patch/patch_funcs/v092/vllm_ascend_adapt.py
ucm/pd/__init__.py
ucm/pd/toy_proxy_server.py
ucm/sparse/__init__.py
ucm/sparse/base.py
ucm/sparse/factory.py
ucm/sparse/state.py
ucm/sparse/utils.py
ucm/sparse/esa/__init__.py
ucm/sparse/esa/esa.py
ucm/sparse/esa/retrieval/__init__.py
ucm/sparse/esa/retrieval/retrieval_backend.cpython-312-x86_64-linux-gnu.so
ucm/sparse/esa/retrieval/retrieval_worker.py
ucm/sparse/gsa/__init__.py
ucm/sparse/gsa/gsa.py
ucm/sparse/gsa/offload_ops/__init__.py
uc_manager-0.1.0rc2.dist-info/METADATA
uc_manager-0.1.0rc2.dist-info/WHEEL
uc_manager-0.1.0rc2.dist-info/top_level.txt
uc_manager-0.1.0rc2.dist-info/RECORD
