Metadata-Version: 2.4
Name: uc-manager
Version: 0.1.0rc2
Summary: Unified Cache Management
Author: Unified Cache Team
Requires-Python: >=3.10
License-File: LICENSE
Requires-Dist: vllm==0.9.2
Dynamic: author
Dynamic: license-file
Dynamic: requires-dist
Dynamic: requires-python
Dynamic: summary
